MANIFEST.in
README
setup.cfg
setup.py
itako/__init__.py
itako/command.py
itako/tests.py
itako.egg-info/PKG-INFO
itako.egg-info/SOURCES.txt
itako.egg-info/dependency_links.txt
itako.egg-info/entry_points.txt
itako.egg-info/top_level.txt