Metadata-Version: 1.1
Name: itako
Version: 0.0.1
Summary: `itako` is a package for development at Itako Inc.
Home-page: https://github.com/Itakoh/itako-py
Author: Ike Tohru
Author-email: ike.tohru@gmail.com
License: BSD
Platform: UNKNOWN
Classifier: Development Status :: 1 - Planning
Classifier: Intended Audience :: Developers
Classifier: Programming Language :: Python
Classifier: Programming Language :: Python :: 2
Classifier: Programming Language :: Python :: 2.7
Classifier: Programming Language :: Python :: 3.4
Classifier: Topic :: Utilities
